avro_gen-0.1.0b2.dist-info/DESCRIPTION.rst
avro_gen-0.1.0b2.dist-info/METADATA
avro_gen-0.1.0b2.dist-info/RECORD
avro_gen-0.1.0b2.dist-info/WHEEL
avro_gen-0.1.0b2.dist-info/metadata.json
avro_gen-0.1.0b2.dist-info/top_level.txt
avrogen/__init__.py
avrogen/core_writer.py
avrogen/dict_wrapper.py
avrogen/namespace.py
avrogen/protocol.py
avrogen/protocol_writer.py
avrogen/schema.py
avrogen/tabbed_writer.py
avrogen/writer.py
