Metadata-Version: 2.0
Name: avro-gen
Version: 0.1.0b2
Summary: Avro record class and specific record reader generator
Home-page: https://github.com/rbystrit/avro_gen
Author: Roman Bystritskiy
Author-email: rbystrit@gmail.com
License: License :: OSI Approved :: Apache Software License
Keywords: avro class generator
Platform: UNKNOWN
Classifier: Development Status :: 4 - Beta
Classifier: Intended Audience :: Developers
Classifier: License :: OSI Approved :: Apache Software License
Classifier: Programming Language :: Python :: 2.7
Requires-Dist: avro (>=1.8.1)
